sqlite_bro/__init__.py
sqlite_bro/sqlite_bro.py
sqlite_bro/tests/__init__.py
sqlite_bro/tests/test_general.py
sqlite_bro-0.12.2.dist-info/LICENSE
sqlite_bro-0.12.2.dist-info/METADATA
sqlite_bro-0.12.2.dist-info/WHEEL
sqlite_bro-0.12.2.dist-info/entry_points.txt
sqlite_bro-0.12.2.dist-info/top_level.txt
sqlite_bro-0.12.2.dist-info/RECORD
