Metadata-Version: 2.1
Name: sqlite-bro
Version: 0.12.2
Summary: a graphic SQLite Client in 1 Python file
Home-page: https://github.com/stonebig/sqlite_bro
Author: stonebig
Author-email: write_pull_requests_to_stonebig@github.com
License: MIT license
Keywords: sqlite,gui,ttk,sql
Platform: UNKNOWN
Classifier: Development Status :: 5 - Production/Stable
Classifier: Environment :: Console
Classifier: Intended Audience :: Education
Classifier: License :: OSI Approved :: MIT License
Classifier: Operating System :: OS Independent
Classifier: Programming Language :: Python
Classifier: Programming Language :: Python :: 2.7
Classifier: Programming Language :: Python :: 3
Classifier: Topic :: Scientific/Engineering :: Information Analysis
License-File: LICENSE
